[
    {
        "created": "20230926010148000",
        "creator": "Deja de seguir adelante",
        "title": "λ:/thoughts-memo-translation-main/refold/detailed/0C Passive Listening",
        "text": "# 0C2：Escucha pasiva\r\n\r\nTexto original：[Passive Listening | Refold](https://refold.la/roadmap/stage-0/c/passive-listening)\r\n\r\nComo se senalo en el articulo anterior, la inmersion activa es la actividad mas importante en la adquisicion de una lengua. Desafortunadamente, puede resultar dificil para las personas ocupadas encontrar suficiente tiempo para una inmersion activa en su vida diaria. Afortunadamente, en tu vida diaria tienes muchas oportunidades de **Escucha pasiva** Su idioma de destino, como cuando cocina, limpia, viaja o hace ejercicio, etc.。\r\n\r\nLo llamamos「Escucha pasiva」，Como no estas completamente concentrado en el contenido, tu atencion se divide entre varias actividades.。\r\n\r\nPuede que estes acostumbrado a escuchar musica o podcasts como entretenimiento durante estas actividades mecanicas, pero te recomendamos que utilices este tiempo para aprender el idioma.。\r\n\r\nLa clave para la escucha pasiva es convertirla en un habito. Cada vez que quieras escuchar audio, la primera opcion debe ser tu idioma de destino. Recomendamos la escucha pasiva al menos una vez al dia. 30 minutos. todos los dias 30 Los minutos se suman, lo que acelerara enormemente tu comprension。\r\n\r\n### Elige que escuchar\r\n\r\nLe recomendamos que escuche repetidamente el contenido en el que se ha sumergido activamente. Porque la repeticion le da a su cerebro la oportunidad de absorber y analizar aun mas el habla y el vocabulario, lo cual es bueno para su cerebro. Desgraciadamente, la repeticion suele resultar aburrida; **El aburrimiento es enemigo del aprendizaje** 。La escucha pasiva es una especie de repeticion sin sentido, que le da a tu cerebro la oportunidad de escuchar nuevamente el contenido en el que te has sumergido activamente.。\r\n\r\nAl principio, es posible que haya muchas cosas que no entiendas, por lo que es clave aprender a tolerar la ambiguedad y seguir escuchando. Escuchar contenido que ya has visto puede ayudarte a mantener el interes porque recordaras la historia incluso si no la entiendes.。\r\n\r\nPara empezar, debes concentrarte en escuchar los sonidos de tu idioma de destino. Puede que no sientas ningun cambio, pero en realidad tu cerebro esta aprendiendo inconscientemente a interpretar sonidos de idiomas extranjeros.。\r\n\r\nA medida que mejoren su vocabulario y sus habilidades para escuchar, desarrollara una comprension mas profunda de lo que esta escuchando pasivamente. Con el tiempo, podras escuchar contenido completamente nuevo, como podcasts, audiolibros y programas de entrevistas.。\r\n\r\nRecuerda， **El aburrimiento es enemigo del aprendizaje** 。Si estas aburrido de lo que escuchas pasivamente, cambia a algo mas interesante.！",
        "type": "text/markdown",
        "caption": " 0C2：Escucha pasiva\r",
        "modified": "20230930171250228",
        "modifier": "Deja de seguir adelante",
        "obvault": "thoughts-memo-translation-main",
        "original-title": "0C Passive Listening"
    }
]