[
    {
        "created": "20230926010148000",
        "creator": "Deja de seguir adelante",
        "title": "λ:/thoughts-memo-translation-main/andy/note/mnemonic-medium/The mnemonic medium may help scaffold prompt-writing through author-provided prompts",
        "text": "# Los medios mnemotecnicos pueden ayudar a escribir tarjetas proporcionando tarjetas creadas por el autor.\r\n\r\nTexto original：[The mnemonic medium may help scaffold prompt-writing through author-provided prompts](https://notes.andymatuschak.org/z4j3bcyJfBzGdpEoQje9gaVeECfsZFgMEhBNL)\r\n\r\n[Los medios mnemotecnicos proporcionan tarjetas escritas por expertos para eliminar la carga de escribirlas.](https://notes.andymatuschak.org/The_mnemonic_medium_supplies_expert-authored_prompts_to_remove_the_burden_of_prompt-writing)，Esto ayuda a aliviar[Escribir tarjetas didacticas con repeticiones espaciadas es dificil](https://notes.andymatuschak.org/z3ntJ7w9C3uapYp1m3gy2EK6PN788guzEoUNN)Pregunta. Sin embargo, el medio mnemotecnico incorporado en estas tarjetas tambien puede ayudar a los lectores que quieran escribir las tarjetas ellos mismos. Pueden ver tarjetas escritas por expertos y utilizarlas como plantillas para sus propias tarjetas.。\r\n\r\nvarias personas[Reino Cuantico](https://notes.andymatuschak.org/z2fBHADWa93EZTuNzuww7V3Vi587ZyZ4FHTHm)de los lectores nos dijeron que intentaron usar Quantum Realm antes de leer Anki，Pero se dieron por vencidos, pero ahora que tienen una idea mas clara de como escribir las tarjetas, lo retoman nuevamente.  Anki 。\r\n\r\nUna variante mas activa：[La incorporacion de plantillas de tarjetas puede ayudar activamente a los lectores de medios mnemotecnicos a escribir tarjetas.](https://notes.andymatuschak.org/z2GSNFzS3TRYHW1UGQhay6Y4J16BVRSwsjWZ)\r\n\r\n## Comentarios de los usuarios sobre este efecto.\r\n\r\n[Giacomo Randazzo Habla sobre el impacto del reino cuantico.](https://notes.andymatuschak.org/z3CeV4YuXgZEJmQQ9mw6B3FV5zkJRjHu14CQc)/[2020-03-28](https://notes.andymatuschak.org/2020-03-28)：\r\n\r\n> 「La serie Quantum Realm me ha ayudado a mejorar Anki Los consejos son muy utiles. Las tarjetas didacticas que contiene estan bien pensadas e incorporan algunas ideas que le ayudaran a descubrir preguntas y respuestas que no son obvias y convertirlas en tarjetas didacticas cuando comience con el material. El autor merece credito por introducir estas ideas gradualmente. Si tiene una buena formacion en matematicas y desea aprender a utilizar el software de repeticion espaciada de forma eficaz, creo que vale la pena tomarse el tiempo para leer toda la serie Quantum Realm.！」[[Fuente1](https://twitter.com/RAN3000/status/1243906206592311296)，[Fuente2](https://twitter.com/RAN3000/status/1243906209679376386)]\r\n\r\n------\r\n\r\n## Referencias\r\n\r\nMatuschak, A. y Nielsen, M. (2019ano10meses). ¿Como podemos desarrollar herramientas de pensamiento transformador?？https://numinous.productions/ttft\r\n\r\n> …Escribir tarjetas de calidad es una habilidad dificil de dominar y las tarjetas que los usuarios elaboran pueden ser de baja calidad, por lo que proporcionar tarjetas de mayor calidad compensara la perdida de los usuarios que no las crean. En el futuro, la cuestion de la necesidad de tarjetas escritas por los usuarios merece un estudio en profundidad. Es necesario demostrar mas rigurosamente y explorar como obtener los beneficios de escribir tarjetas activamente.。",
        "type": "text/markdown",
        "caption": " Los medios mnemotecnicos pueden ayudar a escribir tarjetas proporcionando tarjetas creadas por el autor.\r",
        "modified": "20230930171250222",
        "modifier": "Deja de seguir adelante",
        "obvault": "thoughts-memo-translation-main",
        "original-title": "The mnemonic medium may help scaffold prompt-writing through author-provided prompts"
    }
]