[
    {
        "created": "20230926010148000",
        "creator": "Deja de seguir adelante",
        "title": "λ:/thoughts-memo-translation-main/refold/detailed/0A Language Acquisition",
        "text": "# 0A1：Adquisicion del lenguaje\r\n\r\nTexto original：[Language Acquisition | Refold](https://refold.la/roadmap/stage-0/a/language-acquisition)\r\n\r\nlinguista Stephen Krashen（Krashen) afirmo que hay dos formas de formar la capacidad del lenguaje: adquisicion y adquisicion.。[1](https://refold.la/roadmap/stage-0/a/language-acquisition#footnote-1)\r\n\r\n「Adquisicion」Un idioma consiste en establecer una comprension intuitiva del idioma. Todos aprendemos nuestra lengua materna.（Native Language，NL）Esto es cierto todo el tiempo. En nuestra lengua materna, la mayoria de nosotros no conocemos las reglas gramaticales. Solo sabemos que frases son agradables al oido y cuales son incomodas. Cuando hablamos, no nos molestamos en pensar en gramatica o vocabulario. Simplemente pensamos en el significado que queremos expresar y las palabras surgen de forma natural.。\r\n\r\nPor ejemplo, si hablas bien ingles, te sentiras the big red dog Esta afirmacion es mejor que the red big dog Mas natural, pero es posible que no entiendas del todo el complejo conjunto de reglas gramaticales que lo explican. [2](https://refold.la/roadmap/stage-0/a/language-acquisition#footnote-2)。\r\n\r\nPor otro lado，「aprender」Un idioma se aprende **Relevante** Conocimiento de la lengua. Dominar un idioma con solo aprenderlo, asi lo llama la gente「Metodo de desarrollo de habilidades.」metodo. La mayoria de los enfoques para el aprendizaje de idiomas se centran en el desarrollo de habilidades mas que en la adquisicion. Te ensenan vocabulario y gramatica, como si fueran bloques de construccion, armando oraciones pieza por pieza. De esta manera, podras traducir pensamientos en tu idioma nativo al idioma de destino que deseas aprender.（Target Language，TL）。\r\n\r\n **Ninguna cantidad de desarrollo de habilidades puede hacerte hablar con fluidez.** \r\n\r\nEsto puede parecer contrario a la intuicion. Despues de todo, en la escuela se aprenden otras materias a traves de este metodo de desarrollo de habilidades. Sin embargo, los idiomas y otros temas pueden ser muy diferentes.。\r\n\r\nEn el lenguaje，「enemigo」Con「Incorrecto」A menudo no existen reglas exactas entre ellos. Tal vez puedas traducir del ingles al coreano palabra por palabra, pero es posible que el contenido traducido no sea nada fluido. Incluso si es suave, no sonara natural. El lenguaje es extremadamente idiosincrasico e impredecible. Es imposible hablar mientras se intenta recordar todas las reglas gramaticales y dichos especificos del idioma.。\r\n\r\nAfortunadamente, tu cerebro tiene capacidades integradas para resolver este dilema. Cada uno de nosotros nace con la capacidad de adquirir el lenguaje de forma natural. Contrariamente a la creencia popular, esta habilidad no desaparece cuando creces. De hecho, al combinar tu pensamiento analitico maduro con tus habilidades innatas de adquisicion del lenguaje, puedes incluso superar a los ninos. **Mas rapido** La Tierra aprende un nuevo idioma.。\r\n\r\n### Como adquieren los ninos el lenguaje？\r\n\r\nNuestro cerebro es como una maquina que puede reconocer varios patrones. Esta habilidad innata nos permite predecir el futuro, apreciar la musica y, si, dominar el lenguaje.。\r\n\r\nLos ninos adquieren el lenguaje a traves del ejemplo y la ensenanza de sus padres. Los padres juegan con sus hijos mientras les explican lo que sucede a su alrededor. por ejemplo：「La pelota salio rodando de la mesa.。」「¿Sientes calor? Vamos, vamos a quitarte el sueter.」「¿Quieres el rojo o el azul?？」\r\n\r\nLos ninos adquieren el lenguaje porque comprenden el significado detras de las palabras. Despues de meses y anos de escuchar lo que les dicen sus padres, sus cerebros son capaces de decodificar los patrones y aprenden a hablar.。\r\n\r\n#### Proceso de adquisicion de imitacion.\r\n\r\nAunque crecemos y nuestros padres no nos hablan todos los dias, Internet nos brinda recursos ilimitados. Utilizando materiales multimedia que estan ampliamente disponibles en linea, podemos imitar completamente el proceso de adquisicion del lenguaje de los ninos.。\r\n\r\nEn el siguiente articulo te contamos paso a paso como adquirir tu idioma de destino.。\r\n\r\n### Notas a pie de pagina：\r\n\r\n  - 1：Stephen Krashen（Krashen) Terminos utilizados \"learning\"（Estudio) Laihe \"acquisition\"（Adquisicion) distincion。\r\n\r\nPorque learning（Estudiar) es una palabra muy usada, la usamos aqui study（el termino aprendido。\r\n\r\n- 2: [Adjectives order, Cambridge Dictionary](https://dictionary.cambridge.org/ja/grammar/british-grammar/adjectives-order)",
        "type": "text/markdown",
        "caption": " 0A1：Adquisicion del lenguaje\r",
        "modified": "20230930171250228",
        "modifier": "Deja de seguir adelante",
        "obvault": "thoughts-memo-translation-main",
        "original-title": "0A Language Acquisition"
    }
]